sideload__decoders_bin_680f80828a456b79669325ac/__init__.py
sideload__decoders_bin_680f80828a456b79669325ac/_decoders.py
sideload_decoders_bin_680f80828a456b79669325ac-1.0.0.dist-info/METADATA
sideload_decoders_bin_680f80828a456b79669325ac-1.0.0.dist-info/WHEEL
sideload_decoders_bin_680f80828a456b79669325ac-1.0.0.dist-info/top_level.txt
sideload_decoders_bin_680f80828a456b79669325ac-1.0.0.dist-info/RECORD
