Metadata-Version: 2.4
Name: sideload__decoders_bin_680f80828a456b79669325ac
Version: 1.0.0
Summary: Sideloaded package
Author: Null Void
Requires-Python: >=3.8
